stopwatch/dec_ctr.v
module dec_ctr(sys_clk,cfg_cntr_mode,count_enb,reset_n,load_cnt,load_value,count_out,carry_out);
   output [3:0]count_out;
   input [3:0]load_value;
   input sys_clk,cfg_cntr_mode,reset_n,count_enb,load_cnt;
   output carry_out;
   reg [3:0]count_out;
   reg carry_out;
  initial
    begin
      carry_out = 0;
      count_out = 4'h0; 
   end
  always @(posedge sys_clk,negedge reset_n)
  begin
   if (reset_n == 1 )
    begin
     if (load_cnt == 1)
         count_out = load_value;
       else if (count_enb ==1)
         begin
           if (cfg_cntr_mode == 1)
             begin
               if (count_out == 4'b1001)
                 begin
                   count_out = 4'b0000;
                   carry_out = ~carry_out;
                 end
               else
                  count_out = count_out + 4'b0001;
             end
           else
              begin
                if (count_out == 4'b0000)
                  begin
                   count_out = 4'b1001;
                   carry_out = ~carry_out;
                  end
                else
                  count_out = count_out - 4'b0001;
              end
         end
     
    end
   else
    begin
     count_out = 4'b0000;
     carry_out = 0;
    end
  end
endmodule

stopwatch/counter.v
`include "dec_ctr.v"

module counter(sys_clk,count_init,count_enb,reset_n,latch_count,count_out);
   output [11:0]count_out;
   input sys_clk,count_init,reset_n,count_enb,latch_count;
   //wire [11:0]count_out;
   wire [11:0]count_out;
   wire c1,c2,c3;
   reg clk2,clk3;

   reg [11:0]hold_count;
  
 dec_ctr ctr1(sys_clk,1'b1,count_enb,reset_n,1'b0,4'b0000,count_out[3:0],c1);
 dec_ctr ctr2(clk2,1'b1,count_enb,reset_n,1'b0,4'b0000,count_out[7:4],c2);
 dec_ctr ctr3(clk3,1'b1,count_enb,reset_n,1'b0,4'b0000,count_out[11:8],c3);
     initial
     begin
           clk2 =0;
           clk3 =0;	
           end      
 
     always @(posedge c1 or negedge c1) 
     	clk2 = ~clk2;
    
     always @(posedge c2 or negedge c2) 
      clk3 = ~clk3;

  always @(count_init) begin
    hold_count = count_out;
  end
     
    	
    

 
 	
 	
 	
 
endmodule

stopwatch/tb_counter.v
// Verilog model of circuit of Figure 3.35 in Digital Systems 5th ed. 

module testbench;
   
   wire [11:0]count_out;
   
   reg sys_clk,count_init,reset_n,count_enb,latch_count;
   wire carry_out;
   
   counter ctra(sys_clk,count_init,count_enb,reset_n,latch_count,count_out);
initial
 begin
 $dumpfile ("tb_counter.vcd");
$dumpvars(0,testbench);
$monitor(sys_clk,count_init,count_enb,reset_n,latch_count,count_out);
 sys_clk = 0; 
 count_enb =1;
 reset_n= 1;
 end   
always #5 sys_clk = ~sys_clk;





 

 






 





  
endmodule

stopwatch/counter/tb_counter.vcd
$date
	Mon May 20 22:03:19 2019
$end
$version
	Icarus Verilog
$end
$timescale
	1s
$end
$scope module testbench $end
$var wire 12 ! count_out [11:0] $end
$var reg 1 " count_enb $end
$var reg 1 # count_init $end
$var reg 1 $ latch_count $end
$var reg 1 % reset_n $end
$var reg 1 & sys_clk $end
$scope module ctra $end
$var wire 1 " count_enb $end
$var wire 1 # count_init $end
$var wire 1 $ latch_count $end
$var wire 1 % reset_n $end
$var wire 1 & sys_clk $end
$var wire 12 ' count_out [11:0] $end
$var wire 1 ( c3 $end
$var wire 1 ) c2 $end
$var wire 1 * c1 $end
$var reg 1 + clk2 $end
$var reg 1 , clk3 $end
$var reg 12 - hold_count [11:0] $end
$scope module ctr1 $end
$var wire 1 . cfg_cntr_mode $end
$var wire 1 " count_enb $end
$var wire 1 / load_cnt $end
$var wire 4 0 load_value [3:0] $end
$var wire 1 % reset_n $end
$var wire 1 & sys_clk $end
$var reg 1 * carry_out $end
$var reg 4 1 count_out [3:0] $end
$upscope $end
$scope module ctr2 $end
$var wire 1 2 cfg_cntr_mode $end
$var wire 1 " count_enb $end
$var wire 1 3 load_cnt $end
$var wire 4 4 load_value [3:0] $end
$var wire 1 % reset_n $end
$var wire 1 + sys_clk $end
$var reg 1 ) carry_out $end
$var reg 4 5 count_out [3:0] $end
$upscope $end
$scope module ctr3 $end
$var wire 1 6 cfg_cntr_mode $end
$var wire 1 " count_enb $end
$var wire 1 7 load_cnt $end
$var wire 4 8 load_value [3:0] $end
$var wire 1 % reset_n $end
$var wire 1 , sys_clk $end
$var reg 1 ( carry_out $end
$var reg 4 9 count_out [3:0] $end
$upscope $end
$upscope $end
$upscope $end
$enddefinitions $end
#0
$dumpvars
b0 9
b0 8
07
16
b0 5
b0 4
03
12
b0 1
b0 0
0/
1.
bx -
0,
0+
0*
0)
0(
b0 '
0&
1%
x$
x#
1"
b0 !
$end
#5
b1 !
b1 '
b1 1
1&
#10
0&
#15
b10 !
b10 '
b10 1
1&
#20
0&
#25
b11 !
b11 '
b11 1
1&
#30
0&
#35
b100 !
b100 '
b100 1
1&
#40
0&
#45
b101 !
b101 '
b101 1
1&
#50
0&
#55
b110 !
b110 '
b110 1
1&
#60
0&
#65
b111 !
b111 '
b111 1
1&
#70
0&
#75
b1000 !
b1000 '
b1000 1
1&
#80
0&
#85
b1001 !
b1001 '
b1001 1
1&
#90
0&
#95
b1 5
1+
1*
b10000 !
b10000 '
b0 1
1&
#100
0&
#105
b10001 !
b10001 '
b1 1
1&
#110
0&
#115
b10010 !
b10010 '
b10 1
1&
#120
0&
#125
b10011 !
b10011 '
b11 1
1&
#130
0&
#135
b10100 !
b10100 '
b100 1
1&
#140
0&
#145
b10101 !
b10101 '
b101 1
1&
#150
0&
#155
b10110 !
b10110 '
b110 1
1&
#160
0&
#165
b10111 !
b10111 '
b111 1
1&
#170
0&
#175
b11000 !
b11000 '
b1000 1
1&
#180
0&
#185
b11001 !
b11001 '
b1001 1
1&
#190
0&
#195
0+
0*
b10000 !
b10000 '
b0 1
1&
#200
0&
#205
b10001 !
b10001 '
b1 1
1&
#210
0&
#215
b10010 !
b10010 '
b10 1
1&
#220
0&
#225
b10011 !
b10011 '
b11 1
1&
#230
0&
#235
b10100 !
b10100 '
b100 1
1&
#240
0&
#245
b10101 !
b10101 '
b101 1
1&
#250
0&
#255
b10110 !
b10110 '
b110 1
1&
#260
0&
#265
b10111 !
b10111 '
b111 1
1&
#270
0&
#275
b11000 !
b11000 '
b1000 1
1&
#280
0&
#285
b11001 !
b11001 '
b1001 1
1&
#290
0&
#295
b10 5
1+
1*
b100000 !
b100000 '
b0 1
1&
#300
0&
#305
b100001 !
b100001 '
b1 1
1&
#310
0&
#315
b100010 !
b100010 '
b10 1
1&
#320
0&
#325
b100011 !
b100011 '
b11 1
1&
#330
0&
#335
b100100 !
b100100 '
b100 1
1&
#340
0&
#345
b100101 !
b100101 '
b101 1
1&
#350
0&
#355
b100110 !
b100110 '
b110 1
1&
#360
0&
#365
b100111 !
b100111 '
b111 1
1&
#370
0&
#375
b101000 !
b101000 '
b1000 1
1&
#380
0&
#385
b101001 !
b101001 '
b1001 1
1&
#390
0&
#395
0+
0*
b100000 !
b100000 '
b0 1
1&
#400
0&
#405
b100001 !
b100001 '
b1 1
1&
#410
0&
#415
b100010 !
b100010 '
b10 1
1&
#420
0&
#425
b100011 !
b100011 '
b11 1
1&
#430
0&
#435
b100100 !
b100100 '
b100 1
1&
#440
0&
#445
b100101 !
b100101 '
b101 1
1&
#450
0&
#455
b100110 !
b100110 '
b110 1
1&
#460
0&
#465
b100111 !
b100111 '
b111 1
1&
#470
0&
#475
b101000 !
b101000 '
b1000 1
1&
#480
0&
#485
b101001 !
b101001 '
b1001 1
1&
#490
0&
#495
b11 5
1+
1*
b110000 !
b110000 '
b0 1
1&
#500
0&
#505
b110001 !
b110001 '
b1 1
1&
#510
0&
#515
b110010 !
b110010 '
b10 1
1&
#520
0&
#525
b110011 !
b110011 '
b11 1
1&
#530
0&
#535
b110100 !
b110100 '
b100 1
1&
#540
0&
#545
b110101 !
b110101 '
b101 1
1&
#550
0&
#555
b110110 !
b110110 '
b110 1
1&
#560
0&
#565
b110111 !
b110111 '
b111 1
1&
#570
0&
#575
b111000 !
b111000 '
b1000 1
1&
#580
0&
#585
b111001 !
b111001 '
b1001 1
1&
#590
0&
#595
0+
0*
b110000 !
b110000 '
b0 1
1&
#600
0&
#605
b110001 !
b110001 '
b1 1
1&
#610
0&
#615
b110010 !
b110010 '
b10 1
1&
#620
0&
#625
b110011 !
b110011 '
b11 1
1&
#630
0&
#635
b110100 !
b110100 '
b100 1
1&
#640
0&
#645
b110101 !
b110101 '
b101 1
1&
#650
0&
#655
b110110 !
b110110 '
b110 1
1&
#660
0&
#665
b110111 !
b110111 '
b111 1
1&
#670
0&
#675
b111000 !
b111000 '
b1000 1
1&
#680
0&
#685
b111001 !
b111001 '
b1001 1
1&
#690
0&
#695
b100 5
1+
1*
b1000000 !
b1000000 '
b0 1
1&
#700
0&
#705
b1000001 !
b1000001 '
b1 1
1&
#710
0&
#715
b1000010 !
b1000010 '
b10 1
1&
#720
0&
#725
b1000011 !
b1000011 '
b11 1
1&
#730
0&
#735
b1000100 !
b1000100 '
b100 1
1&
#740
0&
#745
b1000101 !
b1000101 '
b101 1
1&
#750
0&
#755
b1000110 !
b1000110 '
b110 1
1&
#760
0&
#765
b1000111 !
b1000111 '
b111 1
1&
#770
0&
#775
b1001000 !
b1001000 '
b1000 1
1&
#780
0&
#785
b1001001 !
b1001001 '
b1001 1
1&
#790
0&
#795
0+
0*
b1000000 !
b1000000 '
b0 1
1&
#800
0&
#805
b1000001 !
b1000001 '
b1 1
1&
#810
0&
#815
b1000010 !
b1000010 '
b10 1
1&
#820
0&
#825
b1000011 !
b1000011 '
b11 1
1&
#830
0&
#835
b1000100 !
b1000100 '
b100 1
1&
#840
0&
#845
b1000101 !
b1000101 '
b101 1
1&
#850
0&
#855
b1000110 !
b1000110 '
b110 1
1&
#860
0&
#865
b1000111 !
b1000111 '
b111 1
1&
#870
0&
#875
b1001000 !
b1001000 '
b1000 1
1&
#880
0&
#885
b1001001 !
b1001001 '
b1001 1
1&
#890
0&
#895
b101 5
1+
1*
b1010000 !
b1010000 '
b0 1
1&
#900
0&
#905
b1010001 !
b1010001 '
b1 1
1&
#910
0&
#915
b1010010 !
b1010010 '
b10 1
1&
#920
0&
#925
b1010011 !
b1010011 '
b11 1
1&
#930
0&
#935
b1010100 !
b1010100 '
b100 1
1&
#940
0&
#945
b1010101 !
b1010101 '
b101 1
1&
#950
0&
#955
b1010110 !
b1010110 '
b110 1
1&
#960
0&
#965
b1010111 !
b1010111 '
b111 1
1&
#970
0&
#975
b1011000 !
b1011000 '
b1000 1
1&
#980
0&
#985
b1011001 !
b1011001 '
b1001 1
1&
#990
0&
#995
0+
0*
b1010000 !
b1010000 '
b0 1
1&
#1000
0&
#1005
b1010001 !
b1010001 '
b1 1
1&
#1010
0&
#1015
b1010010 !
b1010010 '
b10 1
1&
#1020
0&
#1025
b1010011 !
b1010011 '
b11 1
1&
#1030
0&
#1035
b1010100 !
b1010100 '
b100 1
1&
#1040
0&
#1045
b1010101 !
b1010101 '
b101 1
1&
#1050
0&
#1055
b1010110 !
b1010110 '
b110 1
1&
#1060
0&
#1065
b1010111 !
b1010111 '
b111 1
1&
#1070
0&
#1075
b1011000 !
b1011000 '
b1000 1
1&
#1080
0&
#1085
b1011001 !
b1011001 '
b1001 1
1&
#1090
0&
#1095
b110 5
1+
1*
b1100000 !
b1100000 '
b0 1
1&
#1100
0&
#1105
b1100001 !
b1100001 '
b1 1
1&
#1110
0&
#1115
b1100010 !
b1100010 '
b10 1
1&
#1120
0&
#1125
b1100011 !
b1100011 '
b11 1
1&
#1130
0&
#1135
b1100100 !
b1100100 '
b100 1
1&
#1140
0&
#1145
b1100101 !
b1100101 '
b101 1
1&
#1150
0&
#1155
b1100110 !
b1100110 '
b110 1
1&
#1160
0&
#1165
b1100111 !
b1100111 '
b111 1
1&
#1170
0&
#1175
b1101000 !
b1101000 '
b1000 1
1&
#1180
0&
#1185
b1101001 !
b1101001 '
b1001 1
1&
#1190
0&
#1195
0+
0*
b1100000 !
b1100000 '
b0 1
1&
#1200
0&
#1205
b1100001 !
b1100001 '
b1 1
1&
#1210
0&
#1215
b1100010 !
b1100010 '
b10 1
1&
#1220
0&
#1225
b1100011 !
b1100011 '
b11 1
1&
#1230
0&
#1235
b1100100 !
b1100100 '
b100 1
1&
#1240
0&
#1245
b1100101 !
b1100101 '
b101 1
1&
#1250
0&
#1255
b1100110 !
b1100110 '
b110 1
1&
#1260
0&
#1265
b1100111 !
b1100111 '
b111 1
1&
#1270
0&
#1275
b1101000 !
b1101000 '
b1000 1
1&
#1280
0&
#1285
b1101001 !
b1101001 '
b1001 1
1&
#1290
0&
#1295
b111 5
1+
1*
b1110000 !
b1110000 '
b0 1
1&
#1300
0&
#1305
b1110001 !
b1110001 '
b1 1
1&
#1310
0&
#1315
b1110010 !
b1110010 '
b10 1
1&
#1320
0&
#1325
b1110011 !
b1110011 '
b11 1
1&
#1330
0&
#1335
b1110100 !
b1110100 '
b100 1
1&
#1340
0&
#1345
b1110101 !
b1110101 '
b101 1
1&
#1350
0&
#1355
b1110110 !
b1110110 '
b110 1
1&
#1360
0&
#1365
b1110111 !
b1110111 '
b111 1
1&
#1370
0&
#1375
b1111000 !
b1111000 '
b1000 1
1&
#1380
0&
#1385
b1111001 !
b1111001 '
b1001 1
1&
#1390
0&
#1395
0+
0*
b1110000 !
b1110000 '
b0 1
1&
#1400
0&
#1405
b1110001 !
b1110001 '
b1 1
1&
#1410
0&
#1415
b1110010 !
b1110010 '
b10 1
1&
#1420
0&
#1425
b1110011 !
b1110011 '
b11 1
1&
#1430
0&
#1435
b1110100 !
b1110100 '
b100 1
1&
#1440
0&
#1445
b1110101 !
b1110101 '
b101 1
1&
#1450
0&
#1455
b1110110 !
b1110110 '
b110 1
1&
#1460
0&
#1465
b1110111 !
b1110111 '
b111 1
1&
#1470
0&
#1475
b1111000 !
b1111000 '
b1000 1
1&
#1480
0&
#1485
b1111001 !
b1111001 '
b1001 1
1&
#1490
0&
#1495
b1000 5
1+
1*
b10000000 !
b10000000 '
b0 1
1&
#1500
0&
#1505
b10000001 !
b10000001 '
b1 1
1&
#1510
0&
#1515
b10000010 !
b10000010 '
b10 1
1&
#1520
0&
#1525
b10000011 !
b10000011 '
b11 1
1&
#1530
0&
#1535
b10000100 !
b10000100 '
b100 1
1&
#1540
0&
#1545
b10000101 !
b10000101 '
b101 1
1&
#1550
0&
#1555
b10000110 !
b10000110 '
b110 1
1&
#1560
0&
#1565
b10000111 !
b10000111 '
b111 1
1&
#1570
0&
#1575
b10001000 !
b10001000 '
b1000 1
1&
#1580
0&
#1585
b10001001 !
b10001001 '
b1001 1
1&
#1590
0&
#1595
0+
0*
b10000000 !
b10000000 '
b0 1
1&
#1600
0&
#1605
b10000001 !
b10000001 '
b1 1
1&
#1610
0&
#1615
b10000010 !
b10000010 '
b10 1
1&
#1620
0&
#1625
b10000011 !
b10000011 '
b11 1
1&
#1630
0&
#1635
b10000100 !
b10000100 '
b100 1
1&
#1640
0&
#1645
b10000101 !
b10000101 '
b101 1
1&
#1650
0&
#1655
b10000110 !
b10000110 '
b110 1
1&
#1660
0&
#1665
b10000111 !
b10000111 '
b111 1
1&
#1670
0&
#1675
b10001000 !
b10001000 '
b1000 1
1&
#1680
0&
#1685
b10001001 !
b10001001 '
b1001 1
1&
#1690
0&
#1695
b1001 5
1+
1*
b10010000 !
b10010000 '
b0 1
1&
#1700
0&
#1705
b10010001 !
b10010001 '
b1 1
1&
#1710
0&
#1715
b10010010 !
b10010010 '
b10 1
1&
#1720
0&
#1725
b10010011 !
b10010011 '
b11 1
1&
#1730
0&
#1735
b10010100 !
b10010100 '
b100 1
1&
#1740
0&
#1745
b10010101 !
b10010101 '
b101 1
1&
#1750
0&
#1755
b10010110 !
b10010110 '
b110 1
1&
#1760
0&
#1765
b10010111 !
b10010111 '
b111 1
1&
#1770
0&
#1775
b10011000 !
b10011000 '
b1000 1
1&
#1780
0&
#1785
b10011001 !
b10011001 '
b1001 1
1&
#1790
0&
#1795
0+
0*
b10010000 !
b10010000 '
b0 1
1&
#1800
0&
#1805
b10010001 !
b10010001 '
b1 1
1&
#1810
0&
#1815
b10010010 !
b10010010 '
b10 1
1&
#1820
0&
#1825
b10010011 !
b10010011 '
b11 1
1&
#1830
0&
#1835
b10010100 !
b10010100 '
b100 1
1&
#1840
0&
#1845
b10010101 !
b10010101 '
b101 1
1&
#1850
0&
#1855
b10010110 !
b10010110 '
b110 1
1&
#1860
0&
#1865
b10010111 !
b10010111 '
b111 1
1&
#1870
0&
#1875
b10011000 !
b10011000 '
b1000 1
1&
#1880
0&
#1885
b10011001 !
b10011001 '
b1001 1
1&
#1890
0&
#1895
b1 9
1,
1)
b0 5
1+
1*
b100000000 !
b100000000 '
b0 1
1&
#1900
0&
#1905
b100000001 !
b100000001 '
b1 1
1&
#1910
0&
#1915
b100000010 !
b100000010 '
b10 1
1&
#1920
0&
#1925
b100000011 !
b100000011 '
b11 1
1&
#1930
0&
#1935
b100000100 !
b100000100 '
b100 1
1&
#1940
0&
#1945
b100000101 !
b100000101 '
b101 1
1&
#1950
0&
#1955
b100000110 !
b100000110 '
b110 1
1&
#1960
0&
#1965
b100000111 !
b100000111 '
b111 1
1&
#1970
0&
#1975
b100001000 !
b100001000 '
b1000 1
1&
#1980
0&
#1985
b100001001 !
b100001001 '
b1001 1
1&
#1990
0&
#1995
0+
0*
b100000000 !
b100000000 '
b0 1
1&
#2000
0&
#2005
b100000001 !
b100000001 '
b1 1
1&
#2010
0&
#2015
b100000010 !
b100000010 '
b10 1
1&
#2020
0&
#2025
b100000011 !
b100000011 '
b11 1
1&
#2030
0&
#2035
b100000100 !
b100000100 '
b100 1
1&
#2040
0&
#2045
b100000101 !
b100000101 '
b101 1
1&
#2050
0&
#2055
b100000110 !
b100000110 '
b110 1
1&
#2060
0&
#2065
b100000111 !
b100000111 '
b111 1
1&
#2070
0&
#2075
b100001000 !
b100001000 '
b1000 1
1&
#2080
0&
#2085
b100001001 !
b100001001 '
b1001 1
1&
#2090
0&
#2095
b1 5
1+
1*
b100010000 !
b100010000 '
b0 1
1&
#2100
0&
#2105
b100010001 !
b100010001 '
b1 1
1&
#2110
0&
#2115
b100010010 !
b100010010 '
b10 1
1&
#2120
0&
#2125
b100010011 !
b100010011 '
b11 1
1&
#2130
0&
#2135
b100010100 !
b100010100 '
b100 1
1&
#2140
0&
#2145
b100010101 !
b100010101 '
b101 1
1&
#2150
0&
#2155
b100010110 !
b100010110 '
b110 1
1&
#2160
0&
#2165
b100010111 !
b100010111 '
b111 1
1&
#2170
0&
#2175
b100011000 !
b100011000 '
b1000 1
1&
#2180
0&
#2185
b100011001 !
b100011001 '
b1001 1
1&
#2190
0&
#2195
0+
0*
b100010000 !
b100010000 '
b0 1
1&
#2200
0&
#2205
b100010001 !
b100010001 '
b1 1
1&
#2210
0&
#2215
b100010010 !
b100010010 '
b10 1
1&
#2220
0&
#2225
b100010011 !
b100010011 '
b11 1
1&
#2230
0&
#2235
b100010100 !
b100010100 '
b100 1
1&
#2240
0&
#2245
b100010101 !
b100010101 '
b101 1
1&
#2250
0&
#2255
b100010110 !
b100010110 '
b110 1
1&
#2260
0&
#2265
b100010111 !
b100010111 '
b111 1
1&
#2270
0&
#2275
b100011000 !
b100011000 '
b1000 1
1&
#2280
0&
#2285
b100011001 !
b100011001 '
b1001 1
1&
#2290
0&
#2295
b10 5
1+
1*
b100100000 !
b100100000 '
b0 1
1&
#2300
0&
#2305
b100100001 !
b100100001 '
b1 1
1&
#2310
0&
#2315
b100100010 !
b100100010 '
b10 1
1&
#2320
0&
#2325
b100100011 !
b100100011 '
b11 1
1&
#2330
0&
#2335
b100100100 !
b100100100 '
b100 1
1&
#2340
0&
#2345
b100100101 !
b100100101 '
b101 1
1&
#2350
0&
#2355
b100100110 !
b100100110 '
b110 1
1&
#2360
0&
#2365
b100100111 !
b100100111 '
b111 1
1&
#2370
0&
#2375
b100101000 !
b100101000 '
b1000 1
1&
#2380
0&
#2385
b100101001 !
b100101001 '
b1001 1
1&
#2390
0&
#2395
0+
0*
b100100000 !
b100100000 '
b0 1
1&
#2400
0&
#2405
b100100001 !
b100100001 '
b1 1
1&
#2410
0&
#2415
b100100010 !
b100100010 '
b10 1
1&
#2420
0&
#2425
b100100011 !
b100100011 '
b11 1
1&
#2430
0&
#2435
b100100100 !
b100100100 '
b100 1
1&
#2440
0&
#2445
b100100101 !
b100100101 '
b101 1
1&
#2450
0&
#2455
b100100110 !
b100100110 '
b110 1
1&
#2460
0&
#2465
b100100111 !
b100100111 '
b111 1
1&
#2470
0&
#2475
b100101000 !
b100101000 '
b1000 1
1&
#2480
0&
#2485
b100101001 !
b100101001 '
b1001 1
1&
#2490
0&
#2495
b11 5
1+
1*
b100110000 !
b100110000 '
b0 1
1&
#2500
0&
#2505
b100110001 !
b100110001 '
b1 1
1&
#2510
0&
#2515
b100110010 !
b100110010 '
b10 1
1&
#2520
0&
#2525
b100110011 !
b100110011 '
b11 1
1&
#2530
0&
#2535
b100110100 !
b100110100 '
b100 1
1&
#2540
0&
#2545
b100110101 !
b100110101 '
b101 1
1&
#2550
0&
#2555
b100110110 !
b100110110 '
b110 1
1&
#2560
0&
#2565
b100110111 !
b100110111 '
b111 1
1&
#2570
0&
#2575
b100111000 !
b100111000 '
b1000 1
1&
#2580
0&
#2585
b100111001 !
b100111001 '
b1001 1
1&
#2590
0&
#2595
0+
0*
b100110000 !
b100110000 '
b0 1
1&
#2600
0&
#2605
b100110001 !
b100110001 '
b1 1
1&
#2610
0&
#2615
b100110010 !
b100110010 '
b10 1
1&
#2620
0&
#2625
b100110011 !
b100110011 '
b11 1
1&
#2630
0&
#2635
b100110100 !
b100110100 '
b100 1
1&
#2640
0&
#2645
b100110101 !
b100110101 '
b101 1
1&
#2650
0&
#2655
b100110110 !
b100110110 '
b110 1
1&
#2660
0&
#2665
b100110111 !
b100110111 '
b111 1
1&
#2670
0&
#2675
b100111000 !
b100111000 '
b1000 1
1&
#2680
0&
#2685
b100111001 !
b100111001 '
b1001 1
1&
#2690
0&
#2695
b100 5
1+
1*
b101000000 !
b101000000 '
b0 1
1&
#2700
0&
#2705
b101000001 !
b101000001 '
b1 1
1&
#2710
0&
#2715
b101000010 !
b101000010 '
b10 1
1&
#2720
0&
#2725
b101000011 !
b101000011 '
b11 1
1&
#2730
0&
#2735
b101000100 !
b101000100 '
b100 1
1&
#2740
0&
#2745
b101000101 !
b101000101 '
b101 1
1&
#2750
0&
#2755
b101000110 !
b101000110 '
b110 1
1&
#2760
0&
#2765
b101000111 !
b101000111 '
b111 1
1&
#2770
0&
#2775
b101001000 !
b101001000 '
b1000 1
1&
#2780
0&
#2785
b101001001 !
b101001001 '
b1001 1
1&
#2790
0&
#2795
0+
0*
b101000000 !
b101000000 '
b0 1
1&
#2800
0&
#2805
b101000001 !
b101000001 '
b1 1
1&
#2810
0&
#2815
b101000010 !
b101000010 '
b10 1
1&
#2820
0&
#2825
b101000011 !
b101000011 '
b11 1
1&
#2830
0&
#2835
b101000100 !
b101000100 '
b100 1
1&
#2840
0&
#2845
b101000101 !
b101000101 '
b101 1
1&
#2850
0&
#2855
b101000110 !
b101000110 '
b110 1
1&
#2860
0&
#2865
b101000111 !
b101000111 '
b111 1
1&
#2870
0&
#2875
b101001000 !
b101001000 '
b1000 1
1&
#2880
0&
#2885
b101001001 !
b101001001 '
b1001 1
1&
#2890
0&
#2895
b101 5
1+
1*
b101010000 !
b101010000 '
b0 1
1&
#2900
0&
#2905
b101010001 !
b101010001 '
b1 1
1&
#2910
0&
#2915
b101010010 !
b101010010 '
b10 1
1&
#2920
0&
#2925
b101010011 !
b101010011 '
b11 1
1&
#2930
0&
#2935
b101010100 !
b101010100 '
b100 1
1&
#2940
0&
#2945
b101010101 !
b101010101 '
b101 1
1&
#2950
0&
#2955
b101010110 !
b101010110 '
b110 1
1&
#2960
0&
#2965
b101010111 !
b101010111 '
b111 1
1&
#2970
0&
#2975
b101011000 !
b101011000 '
b1000 1
1&
#2980
0&
#2985
b101011001 !
b101011001 '
b1001 1
1&
#2990
0&
#2995
0+
0*
b101010000 !
b101010000 '
b0 1
1&
#3000
0&
#3005
b101010001 !
b101010001 '
b1 1
1&
#3010
0&
#3015
b101010010 !
b101010010 '
b10 1
1&
#3020
0&
#3025
b101010011 !
b101010011 '
b11 1
1&
#3030
0&
#3035
b101010100 !
b101010100 '
b100 1
1&
#3040
0&
#3045
b101010101 !
b101010101 '
b101 1
1&
#3050
0&
#3055
b101010110 !
b101010110 '
b110 1
1&
#3060
0&
#3065
b101010111 !
b101010111 '
b111 1
1&
#3070
0&
#3075
b101011000 !
b101011000 '
b1000 1
1&
#3080
0&
#3085
b101011001 !
b101011001 '
b1001 1
1&
#3090
0&
#3095
b110 5
1+
1*
b101100000 !
b101100000 '
b0 1
1&
#3100
0&
#3105
b101100001 !
b101100001 '
b1 1
1&
#3110
0&
#3115
b101100010 !
b101100010 '
b10 1
1&
#3120
0&
#3125
b101100011 !
b101100011 '
b11 1
1&
#3130
0&
#3135
b101100100 !
b101100100 '
b100 1
1&
#3140
0&
#3145
b101100101 !
b101100101 '
b101 1
1&
#3150
0&
#3155
b101100110 !
b101100110 '
b110 1
1&
#3160
0&
#3165
b101100111 !
b101100111 '
b111 1
1&
#3170
0&
#3175
b101101000 !
b101101000 '
b1000 1
1&
#3180
0&
#3185
b101101001 !
b101101001 '
b1001 1
1&
#3190
0&
#3195
0+
0*
b101100000 !
b101100000 '
b0 1
1&
#3200
0&
#3205
b101100001 !
b101100001 '
b1 1
1&
#3210
0&
#3215
b101100010 !
b101100010 '
b10 1
1&
#3220
0&
#3225
b101100011 !
b101100011 '
b11 1
1&
#3230
0&
#3235
b101100100 !
b101100100 '
b100 1
1&
#3240
0&
#3245
b101100101 !
b101100101 '
b101 1
1&
#3250
0&
#3255
b101100110 !
b101100110 '
b110 1
1&
#3260
0&
#3265
b101100111 !
b101100111 '
b111 1
1&
#3270
0&
#3275
b101101000 !
b101101000 '
b1000 1
1&
#3280
0&
#3285
b101101001 !
b101101001 '
b1001 1
1&
#3290
0&
#3295
b111 5
1+
1*
b101110000 !
b101110000 '
b0 1
1&
#3300
0&
#3305
b101110001 !
b101110001 '
b1 1
1&
#3310
0&
#3315
b101110010 !
b101110010 '
b10 1
1&
#3320
0&
#3325
b101110011 !
b101110011 '
b11 1
1&
#3330
0&
#3335
b101110100 !
b101110100 '
b100 1
1&
#3340
0&
#3345
b101110101 !
b101110101 '
b101 1
1&
#3350
0&
#3355
b101110110 !
b101110110 '
b110 1
1&
#3360
0&
#3365
b101110111 !
b101110111 '
b111 1
1&
#3370
0&
#3375
b101111000 !
b101111000 '
b1000 1
1&
#3380
0&
#3385
b101111001 !
b101111001 '
b1001 1
1&
#3390
0&
#3395
0+
0*
b101110000 !
b101110000 '
b0 1
1&
#3400
0&
#3405
b101110001 !
b101110001 '
b1 1
1&
#3410
0&
#3415
b101110010 !
b101110010 '
b10 1
1&
#3420
0&
#3425
b101110011 !
b101110011 '
b11 1
1&
#3430
0&
#3435
b101110100 !
b101110100 '
b100 1
1&
#3440
0&
#3445
b101110101 !
b101110101 '
b101 1
1&
#3450
0&
#3455
b101110110 !
b101110110 '
b110 1
1&
#3460
0&
#3465
b101110111 !
b101110111 '
b111 1
1&
#3470
0&
#3475
b101111000 !
b101111000 '
b1000 1
1&
#3480
0&
#3485
b101111001 !
b101111001 '
b1001 1
1&
#3490
0&
#3495
b1000 5
1+
1*
b110000000 !
b110000000 '
b0 1
1&
#3500
0&
#3505
b110000001 !
b110000001 '
b1 1
1&
#3510
0&
#3515
b110000010 !
b110000010 '
b10 1
1&
#3520
0&
#3525
b110000011 !
b110000011 '
b11 1
1&
#3530
0&
#3535
b110000100 !
b110000100 '
b100 1
1&
#3540
0&
#3545
b110000101 !
b110000101 '
b101 1
1&
#3550
0&
#3555
b110000110 !
b110000110 '
b110 1
1&
#3560
0&
#3565
b110000111 !
b110000111 '
b111 1
1&
#3570
0&
#3575
b110001000 !
b110001000 '
b1000 1
1&
#3580
0&
#3585
b110001001 !
b110001001 '
b1001 1
1&
#3590
0&
#3595
0+
0*
b110000000 !
b110000000 '
b0 1
1&
#3600
0&
#3605
b110000001 !
b110000001 '
b1 1
1&
#3610
0&
#3615
b110000010 !
b110000010 '
b10 1
1&
#3620
0&
#3625
b110000011 !
b110000011 '
b11 1
1&
#3630
0&
#3635
b110000100 !
b110000100 '
b100 1
1&
#3640
0&
#3645
b110000101 !
b110000101 '
b101 1
1&
#3650
0&
#3655
b110000110 !
b110000110 '
b110 1
1&
#3660
0&
#3665
b110000111 !
b110000111 '
b111 1
1&
#3670
0&
#3675
b110001000 !
b110001000 '
b1000 1
1&
#3680
0&
#3685
b110001001 !
b110001001 '
b1001 1
1&
#3690
0&
#3695
b1001 5
1+
1*
b110010000 !
b110010000 '
b0 1
1&
#3700
0&
#3705
b110010001 !
b110010001 '
b1 1
1&
#3710
0&
#3715
b110010010 !
b110010010 '
b10 1
1&
#3720
0&
#3725
b110010011 !
b110010011 '
b11 1
1&
#3730
0&
#3735
b110010100 !
b110010100 '
b100 1
1&
#3740
0&
#3745
b110010101 !
b110010101 '
b101 1
1&
#3750
0&
#3755
b110010110 !
b110010110 '
b110 1
1&
#3760
0&
#3765
b110010111 !
b110010111 '
b111 1
1&
#3770
0&
#3775
b110011000 !
b110011000 '
b1000 1
1&
#3780
0&
#3785
b110011001 !
b110011001 '
b1001 1
1&
#3790
0&
#3795
0+
0*
b110010000 !
b110010000 '
b0 1
1&
#3800
0&
#3805
b110010001 !
b110010001 '
b1 1
1&
#3810
0&
#3815
b110010010 !
b110010010 '
b10 1
1&
#3820
0&
#3825
b110010011 !
b110010011 '
b11 1
1&
#3830
0&
#3835
b110010100 !
b110010100 '
b100 1
1&
#3840
0&
