stopwatch/dec_ctr.v
module dec_ctr(sys_clk,cfg_cntr_mode,count_enb,reset_n,load_cnt,load_value,count_out,carry_out);
   output [3:0]count_out;
   input [3:0]load_value;
   input sys_clk,cfg_cntr_mode,reset_n,count_enb,load_cnt;
   output carry_out;
   reg [3:0]count_out;
   reg carry_out;
  initial
    begin
      carry_out = 0;
      count_out = 4'h0; 
   end
  always @(posedge sys_clk,negedge reset_n)
  begin
   if (reset_n == 1 )
    begin
     if (load_cnt == 1)
         count_out = load_value;
       else if (count_enb ==1)
         begin
           if (cfg_cntr_mode == 1)
             begin
               if (count_out == 4'b1001)
                 begin
                   count_out = 4'b0000;
                   carry_out = ~carry_out;
                 end
               else
                  count_out = count_out + 4'b0001;
             end
           else
              begin
                if (count_out == 4'b0000)
                  begin
                   count_out = 4'b1001;
                   carry_out = ~carry_out;
                  end
                else
                  count_out = count_out - 4'b0001;
              end
         end
     
    end
   else
    begin
     count_out = 4'b0000;
     carry_out = 0;
    end
  end
endmodule

stopwatch/dec_ctr/tb_dec_ctr.v
// Verilog model of circuit of Figure 3.35 in Digital Systems 5th ed. 

module testbench;
   
   wire [3:0]count_out;
   reg [3:0]load_value;
   reg sys_clk,cfg_cntr_mode,reset_n,count_enb,load_cnt;
   wire carry_out;
   
dec_ctr ctr1(sys_clk,cfg_cntr_mode,count_enb,reset_n,load_cnt,load_value,count_out,carry_out);
initial
 begin
 $dumpfile ("tb_dec_ctr.vcd");
$dumpvars(0,testbench);
$monitor(sys_clk,cfg_cntr_mode,count_enb,reset_n,load_cnt,load_value,count_out,carry_out);
 sys_clk = 0; 
 end   
always #5 sys_clk = ~sys_clk;
initial
 begin 

 cfg_cntr_mode = 1;  //load count check
 reset_n= 1;
 load_cnt =1;
 count_enb =0;
 #10 load_value= 4'b0111;
 #10 load_value = 4'b0101;
 #10 load_value = 4'b0100;

 #10 load_cnt = 0;   //up counter check
     count_enb =1;
 #45
 
 #10 cfg_cntr_mode = 0;  //down_counter check
 #45  
 #10 count_enb = 0;
 #10 count_enb = 0;
 #10 count_enb = 0;
 #10 reset_n =0;
 #10 reset_n =0;




 

 end






 





  
endmodule

stopwatch/dec_ctr/tb_dec_ctr.vcd
$date
	Wed Apr 24 21:13:54 2019
$end
$version
	Icarus Verilog
$end
$timescale
	1s
$end
$scope module testbench $end
$var wire 4 ! count_out [3:0] $end
$var wire 1 " carry_out $end
$var reg 1 # cfg_cntr_mode $end
$var reg 1 $ count_enb $end
$var reg 1 % load_cnt $end
$var reg 4 & load_value [3:0] $end
$var reg 1 ' reset_n $end
$var reg 1 ( sys_clk $end
$scope module ctr1 $end
$var wire 1 # cfg_cntr_mode $end
$var wire 1 $ count_enb $end
$var wire 1 % load_cnt $end
$var wire 4 ) load_value [3:0] $end
$var wire 1 ' reset_n $end
$var wire 1 ( sys_clk $end
$var reg 1 " carry_out $end
$var reg 4 * count_out [3:0] $end
$upscope $end
$upscope $end
$enddefinitions $end
#0
$dumpvars
b0 *
bx )
0(
1'
bx &
1%
0$
1#
0"
b0 !
$end
#5
bx !
bx *
1(
#10
0(
b111 &
b111 )
#15
b111 !
b111 *
1(
#20
0(
b101 &
b101 )
#25
b101 !
b101 *
1(
#30
0(
b100 &
b100 )
#35
b100 !
b100 *
1(
#40
0(
1$
0%
#45
b101 !
b101 *
1(
#50
0(
#55
b110 !
b110 *
1(
#60
0(
#65
b111 !
b111 *
1(
#70
0(
#75
b1000 !
b1000 *
1(
#80
0(
#85
b1001 !
b1001 *
1(
#90
0(
#95
b1000 !
b1000 *
1(
0#
#100
0(
#105
b111 !
b111 *
1(
#110
0(
#115
b110 !
b110 *
1(
#120
0(
#125
b101 !
b101 *
1(
#130
0(
#135
b100 !
b100 *
1(
#140
0(
#145
b11 !
b11 *
1(
#150
0(
0$
#155
1(
#160
0(
#165
1(
#170
0(
#175
1(
#180
b0 !
b0 *
0(
0'
